{
    "searchParameters": {
        "q": "site:krafton.com (\"global\" OR \"worldwide\" OR \"coverage\" OR \"international\")",
        "gl": "us",
        "hl": "en",
        "type": "search",
        "num": 10,
        "engine": "google"
    },
    "organic": [
        {
            "title": "KRAFTON LAUNCHES KRAFTON CREATOR NETWORK ...",
            "link": "https://press.krafton.com/KRAFTON-LAUNCHES-KRAFTON-CREATOR-NETWORK-TO-EMPOWER-GLOBAL-GAME-CREATO",
            "snippet": "... global marketing and support program designed to empower gaming content creators. The KCN program is open to eligible creators worldwide who ...",
            "date": "Mar 13, 2025",
            "position": 1
        },
        {
            "title": "KRAFTON HOSTS INZOI GLOBAL SHOWCASE",
            "link": "https://krafton.com/en/news/press/krafton-hosts-inzoi-global-showcase/",
            "snippet": "The full global showcase can be viewed on inZOI's official YouTube channel here. Meanwhile, KRAFTON will release the inZOI: Creative Studio demo ...",
            "date": "Mar 19, 2025",
            "position": 2
        },
        {
            "title": "DARK AND DARKER MOBILE'S FIRST GLOBAL BETA ...",
            "link": "https://press.krafton.com/DARK-AND-DARKER-MOBILES-FIRST-GLOBAL-BETA-TEST-STARTS",
            "snippet": "This test, the first outside of South Korea, was organised to meet the high expectations of international users. ... global release later in 2024.",
            "date": "Aug 1, 2024",
            "position": 3
        },
        {
            "title": "Global Publishing Platform Dept. - KRAFTON",
            "link": "https://blog.krafton.com/tag/global-publishing-platform-dept/",
            "snippet": "Tag - Global Publishing Platform Dept. PeopleOn English ver. Developers who support developers, Global... © KRAFTON, Inc. All rights reserved.",
            "position": 4
        },
        {
            "title": "KRAFTON ANNOUNCES INZOI GLOBAL SHOWCASE TO ...",
            "link": "https://krafton.com/en/news/press/krafton-announces-inzoi-global-showcase-to-be-held-on-march-19/",
            "snippet": "Press. Game. KRAFTON ANNOUNCES INZOI GLOBAL SHOWCASE TO BE HELD ON MARCH 19 ... Prev. KRAFTON SIGNS GLOBAL PUBLISHING DEAL FOR PC SURVIVAL LIFE SIM DINKUM ...",
            "position": 5
        },
        {
            "title": "Dark and Darker Mobile Soft Launch Begins!",
            "link": "https://dndm.krafton.com/en/news/8187",
            "snippet": "The Canada/U.S. servers will remain available after the global launch, and all progress made during the soft launch on only these servers will ...",
            "date": "Feb 4, 2025",
            "position": 6
        },
        {
            "title": "KRAFTON TO HOST A DARK AND DARKER MOBILE ...",
            "link": "https://press.krafton.com/en-US/KRAFTON-TO-HOST-A-DARK-AND-DARKER-MOBILE-GLOBAL-BETA-TEST-AUGUST-1-11",
            "snippet": "Following the Global Beta Test in late August, KRAFTON will showcase ... worldwide. Founded in 2007, KRAFTON consists of PUBG STUDIOS ...",
            "date": "Jul 17, 2024",
            "position": 7
        },
        {
            "title": "KRAFTON LAUNCHES INZOI IN GLOBAL EARLY ACCESS",
            "link": "https://press.krafton.com/KRAFTON-LAUNCHES-INZOI-IN-GLOBAL-EARLY-ACCESS",
            "snippet": "Notably, the inZOI global showcase held on March 19 successfully attracted over 450,000 viewers. ... worldwide, offering a chance to experience ...",
            "date": "Mar 28, 2025",
            "currency": "$",
            "price": 39.99,
            "position": 8
        },
        {
            "title": "Press | KRAFTON",
            "link": "https://www.krafton.com/en/news/press/?var_page=6",
            "snippet": "06. KRAFTON Welcomes Jin Oh as Chief Global Publishing Officer Krafton's global publishing capabilities strengthened by Oh's international experience at ...",
            "position": 9
        },
        {
            "title": "PUBG GLOBAL CHAMPIONSHIP 2024",
            "link": "https://wstatic-prod-boc.krafton.com/common/default/20241206/1tyjv0P1/PUBG%20GLOBAL%20CHAMPIONSHIP%202024_Tournament_Rules_EN_1206.pdf",
            "snippet": "PUBG GLOBAL CHAMPIONSHIP 2024 (“PGC” or “Competition” or “Tournament ... Interviews will be made public worldwide, just as the official matches. If a ...",
            "position": 10
        }
    ],
    "credits": 1
}