{
    "searchParameters": {
        "q": "site:krafton.com (\"multiplayer\" OR \"service\" OR \"game\")",
        "gl": "us",
        "hl": "en",
        "type": "search",
        "num": 10,
        "engine": "google"
    },
    "organic": [
        {
            "title": "ReLU Games | KRAFTON",
            "link": "https://krafton.com/en/studios/relugames/",
            "snippet": "The internet introduced us to 'online/multiplayer play' as a genre ... Scavenger T.O.M is a survival crafting game set in a radiation-contaminated world.",
            "position": 1
        },
        {
            "title": "Project ZETA",
            "link": "https://zeta.krafton.com/",
            "snippet": "TERMS OF SERVICE|PRIVACY POLICY|COOKIE POLICY| COOKIE SETTINGS. © 2025 ... The game, including but not limited to its gameplay mechanics, graphics ...",
            "position": 2
        },
        {
            "title": "KRAFTON LAUNCHES INZOI IN GLOBAL EARLY ACCESS",
            "link": "https://krafton.com/en/news/press/krafton-launches-inzoi-in-global-early-access/",
            "snippet": "inZOI is available in Early Access via Steam from March 28. The game is set at a price of $39.99, with all updates and DLC to be provided for free until full ...",
            "position": 3
        },
        {
            "title": "Defense Derby | KRAFTON",
            "link": "https://krafton.com/en/games/defensederby/",
            "snippet": "Engage in a fierce battle of wits to recruit your units.​. You can recruit units with Derby Chips. From daring early-game bets to resilient late-game ...",
            "position": 4
        },
        {
            "title": "Dinkum Together",
            "link": "https://dinkumtogether.krafton.com/en",
            "snippet": "game logo. News. Media. MORE. News; Media. ENGLISH. ENGLISH; 한국어 ... 5MINLAB IS A REGISTERED TRADEMARK OR SERVICE MARK OF KRAFTON, INC. Our site uses cookies ...",
            "position": 5
        },
        {
            "title": "Dreamotion",
            "link": "https://krafton.com/en/studios/dreamotion/",
            "snippet": "Our focus is on the game's core essence, “FUN”. Once we are convinced that this will be a fun game, we will make it, regardless of the genre or platform.",
            "position": 6
        },
        {
            "title": "STRIKING DISTANCE STUDIOS GOES ROGUE WITH ITS ...",
            "link": "https://press.krafton.com/STRIKING-DISTANCE-STUDIOS-GOES-ROGUE-WITH-ITS-NEW-GAME-REDACTED",
            "snippet": "This game is all about fighting, dying, dying again, dying some more, and adapting, taking the classic roguelike formula and cranking it to ...",
            "date": "Aug 22, 2024",
            "position": 7
        },
        {
            "title": "Games | KRAFTON",
            "link": "https://krafton.com/en/games/",
            "snippet": "Commander Quest. Deckbuilding Roguelike, Card Game, Strategy; PC. More. Flyway Games. TOP. Visit Us · Privacy Policy · Contact Us · Speak Up · Privacy Notice ...",
            "sitelinks": [
                {
                    "title": "inZOI",
                    "link": "https://krafton.com/en/games/inzoi/"
                },
                {
                    "title": "Pubg: battlegrounds",
                    "link": "https://krafton.com/en/games/battlegrounds/"
                },
                {
                    "title": "Commander Quest",
                    "link": "https://krafton.com/en/games/commander-quest/"
                },
                {
                    "title": "TERA",
                    "link": "https://www.krafton.com/en/games/tera/"
                }
            ],
            "position": 8
        },
        {
            "title": "Rivals Hover League - Official Site",
            "link": "https://rivals.krafton.com/",
            "snippet": "... Rivals Hover League' is a vehicular combat PvP game where you harness the unique abilities of hover vehicles ... Terms of Service|Privacy Policy ...",
            "position": 9
        },
        {
            "title": "inZOI | KRAFTON",
            "link": "https://krafton.com/en/games/inzoi/",
            "snippet": "On-device generative AI tools empower players to easily create personalized customizations. Game Platform. inZOI (Steam). Steam Website · 5minlab. DEVELOPER ...",
            "position": 10
        }
    ],
    "relatedSearches": [
        {
            "query": "Video game multiplayer service game"
        },
        {
            "query": "Multiplayer service game switch"
        },
        {
            "query": "Multiplayer service game xbox"
        },
        {
            "query": "Best multiplayer service game"
        }
    ],
    "credits": 1
}